{"id":"LZ4BHK9OGOY3I","name":"original_b9571e9da924ed9d96a44a896013301a.jpg","size":4065279,"btime":1722095987685,"mtime":1722095987688,"ext":"png","tags":[],"folders":[],"isDeleted":false,"url":"","annotation":"","modificationTime":1722095987684,"height":4095,"width":4095,"lastModified":1722104884489,"palettes":[{"color":[4,4,4],"ratio":94},{"color":[169,173,181],"ratio":2.85},{"color":[85,93,102],"ratio":1.22},{"color":[39,47,56],"ratio":0.45},{"color":[102,118,138],"ratio":0.38},{"color":[57,74,89],"ratio":0.36},{"color":[46,57,70],"ratio":0.32}]}